gitgood/__init__.py
gitgood/main.py
gitgood-0.1.0a1.dist-info/entry_points.txt
gitgood-0.1.0a1.dist-info/LICENSE
gitgood-0.1.0a1.dist-info/WHEEL
gitgood-0.1.0a1.dist-info/METADATA
gitgood-0.1.0a1.dist-info/RECORD
