Metadata-Version: 2.1
Name: gitgood
Version: 0.1.0a1
Summary: 
License: Apache-2.0
Author: QEDK
Author-email: qedk.en@gmail.com
Requires-Python: >=3.7,<4.0
Classifier: License :: OSI Approved :: Apache Software License
Classifier: Programming Language :: Python :: 3
Classifier: Programming Language :: Python :: 3.7
Classifier: Programming Language :: Python :: 3.8
Classifier: Programming Language :: Python :: 3.9
Requires-Dist: PyGithub (>=1.53,<2.0)
Requires-Dist: python-dotenv (>=0.15.0,<0.16.0)
Requires-Dist: typer[all] (>=0.3.2,<0.4.0)
